{
    "replace":  false,
    "values":  [
                   {
                       "id":  "mineclawd:dynamic_fluid_001",
                       "required":  false
                   },
                   {
                       "id":  "mineclawd:flowing_dynamic_fluid_001",
                       "required":  false
                   },
                   {
                       "id":  "mineclawd:dynamic_fluid_002",
                       "required":  false
                   },
                   {
                       "id":  "mineclawd:flowing_dynamic_fluid_002",
                       "required":  false
                   },
                   {
                       "id":  "mineclawd:dynamic_fluid_003",
                       "required":  false
                   },
                   {
                       "id":  "mineclawd:flowing_dynamic_fluid_003",
                       "required":  false
                   },
                   {
                       "id":  "mineclawd:dynamic_fluid_004",
                       "required":  false
                   },
                   {
                       "id":  "mineclawd:flowing_dynamic_fluid_004",
                       "required":  false
                   },
                   {
                       "id":  "mineclawd:dynamic_fluid_005",
                       "required":  false
                   },
                   {
                       "id":  "mineclawd:flowing_dynamic_fluid_005",
                       "required":  false
                   },
                   {
                       "id":  "mineclawd:dynamic_fluid_006",
                       "required":  false
                   },
                   {
                       "id":  "mineclawd:flowing_dynamic_fluid_006",
                       "required":  false
                   },
                   {
                       "id":  "mineclawd:dynamic_fluid_007",
                       "required":  false
                   },
                   {
                       "id":  "mineclawd:flowing_dynamic_fluid_007",
                       "required":  false
                   },
                   {
                       "id":  "mineclawd:dynamic_fluid_008",
                       "required":  false
                   },
                   {
                       "id":  "mineclawd:flowing_dynamic_fluid_008",
                       "required":  false
                   },
                   {
                       "id":  "mineclawd:dynamic_fluid_009",
                       "required":  false
                   },
                   {
                       "id":  "mineclawd:flowing_dynamic_fluid_009",
                       "required":  false
                   },
                   {
                       "id":  "mineclawd:dynamic_fluid_010",
                       "required":  false
                   },
                   {
                       "id":  "mineclawd:flowing_dynamic_fluid_010",
                       "required":  false
                   },
                   {
                       "id":  "mineclawd:dynamic_fluid_011",
                       "required":  false
                   },
                   {
                       "id":  "mineclawd:flowing_dynamic_fluid_011",
                       "required":  false
                   },
                   {
                       "id":  "mineclawd:dynamic_fluid_012",
                       "required":  false
                   },
                   {
                       "id":  "mineclawd:flowing_dynamic_fluid_012",
                       "required":  false
                   },
                   {
                       "id":  "mineclawd:dynamic_fluid_013",
                       "required":  false
                   },
                   {
                       "id":  "mineclawd:flowing_dynamic_fluid_013",
                       "required":  false
                   },
                   {
                       "id":  "mineclawd:dynamic_fluid_014",
                       "required":  false
                   },
                   {
                       "id":  "mineclawd:flowing_dynamic_fluid_014",
                       "required":  false
                   },
                   {
                       "id":  "mineclawd:dynamic_fluid_015",
                       "required":  false
                   },
                   {
                       "id":  "mineclawd:flowing_dynamic_fluid_015",
                       "required":  false
                   },
                   {
                       "id":  "mineclawd:dynamic_fluid_016",
                       "required":  false
                   },
                   {
                       "id":  "mineclawd:flowing_dynamic_fluid_016",
                       "required":  false
                   },
                   {
                       "id":  "mineclawd:dynamic_fluid_017",
                       "required":  false
                   },
                   {
                       "id":  "mineclawd:flowing_dynamic_fluid_017",
                       "required":  false
                   },
                   {
                       "id":  "mineclawd:dynamic_fluid_018",
                       "required":  false
                   },
                   {
                       "id":  "mineclawd:flowing_dynamic_fluid_018",
                       "required":  false
                   },
                   {
                       "id":  "mineclawd:dynamic_fluid_019",
                       "required":  false
                   },
                   {
                       "id":  "mineclawd:flowing_dynamic_fluid_019",
                       "required":  false
                   },
                   {
                       "id":  "mineclawd:dynamic_fluid_020",
                       "required":  false
                   },
                   {
                       "id":  "mineclawd:flowing_dynamic_fluid_020",
                       "required":  false
                   },
                   {
                       "id":  "mineclawd:dynamic_fluid_021",
                       "required":  false
                   },
                   {
                       "id":  "mineclawd:flowing_dynamic_fluid_021",
                       "required":  false
                   },
                   {
                       "id":  "mineclawd:dynamic_fluid_022",
                       "required":  false
                   },
                   {
                       "id":  "mineclawd:flowing_dynamic_fluid_022",
                       "required":  false
                   },
                   {
                       "id":  "mineclawd:dynamic_fluid_023",
                       "required":  false
                   },
                   {
                       "id":  "mineclawd:flowing_dynamic_fluid_023",
                       "required":  false
                   },
                   {
                       "id":  "mineclawd:dynamic_fluid_024",
                       "required":  false
                   },
                   {
                       "id":  "mineclawd:flowing_dynamic_fluid_024",
                       "required":  false
                   },
                   {
                       "id":  "mineclawd:dynamic_fluid_025",
                       "required":  false
                   },
                   {
                       "id":  "mineclawd:flowing_dynamic_fluid_025",
                       "required":  false
                   },
                   {
                       "id":  "mineclawd:dynamic_fluid_026",
                       "required":  false
                   },
                   {
                       "id":  "mineclawd:flowing_dynamic_fluid_026",
                       "required":  false
                   },
                   {
                       "id":  "mineclawd:dynamic_fluid_027",
                       "required":  false
                   },
                   {
                       "id":  "mineclawd:flowing_dynamic_fluid_027",
                       "required":  false
                   },
                   {
                       "id":  "mineclawd:dynamic_fluid_028",
                       "required":  false
                   },
                   {
                       "id":  "mineclawd:flowing_dynamic_fluid_028",
                       "required":  false
                   },
                   {
                       "id":  "mineclawd:dynamic_fluid_029",
                       "required":  false
                   },
                   {
                       "id":  "mineclawd:flowing_dynamic_fluid_029",
                       "required":  false
                   },
                   {
                       "id":  "mineclawd:dynamic_fluid_030",
                       "required":  false
                   },
                   {
                       "id":  "mineclawd:flowing_dynamic_fluid_030",
                       "required":  false
                   }
               ]
}

